cli/swocli.py
cli/core/alias_group.py
cli/core/console.py
cli/core/errors.py
cli/core/plugins.py
cli/core/state.py
cli/core/stats.py
cli/core/utils.py
cli/core/accounts/__init__.py
cli/core/accounts/app.py
cli/core/accounts/constants.py
cli/core/accounts/containers.py
cli/core/accounts/flows.py
cli/core/accounts/models.py
cli/core/accounts/handlers/__init__.py
cli/core/accounts/handlers/json_file_handler.py
cli/core/handlers/__init__.py
cli/core/handlers/constants.py
cli/core/handlers/errors.py
cli/core/handlers/excel_file_handler.py
cli/core/handlers/excel_styles.py
cli/core/handlers/file_handler.py
cli/core/handlers/file_manager.py
cli/core/handlers/horizontal_tab_file_manager.py
cli/core/handlers/vertical_tab_file_manager.py
cli/core/icons/fake-icon.png
cli/core/models/__init__.py
cli/core/models/data_model.py
cli/core/mpt/__init__.py
cli/core/mpt/api.py
cli/core/mpt/client.py
cli/core/mpt/flows.py
cli/core/mpt/models.py
cli/core/price_lists/__init__.py
cli/core/price_lists/app.py
cli/core/price_lists/constants.py
cli/core/price_lists/api/__init__.py
cli/core/price_lists/api/price_list_api_service.py
cli/core/price_lists/api/price_list_item_api_service.py
cli/core/price_lists/handlers/__init__.py
cli/core/price_lists/handlers/price_list_excel_file_manager.py
cli/core/price_lists/handlers/price_list_item_excel_file_manager.py
cli/core/price_lists/models/__init__.py
cli/core/price_lists/models/item.py
cli/core/price_lists/models/price_list.py
cli/core/price_lists/services/__init__.py
cli/core/price_lists/services/item_service.py
cli/core/price_lists/services/price_list_service.py
cli/core/products/__init__.py
cli/core/products/app.py
cli/core/products/constants.py
cli/core/products/containers.py
cli/core/products/api/__init__.py
cli/core/products/api/item_api_service.py
cli/core/products/api/item_group_api_service.py
cli/core/products/api/parameter_group_api_service.py
cli/core/products/api/parameters_api_service.py
cli/core/products/api/product_api_service.py
mpt_cli-5.3.0.dist-info/METADATA
mpt_cli-5.3.0.dist-info/WHEEL
mpt_cli-5.3.0.dist-info/entry_points.txt
mpt_cli-5.3.0.dist-info/licenses/LICENSE
mpt_cli-5.3.0.dist-info/RECORD
