Metadata-Version: 2.4
Name: mpt-cli
Version: 5.3.0
Summary: Command line utility for SoftwareOne Marketplace Platform
Author: SoftwareOne AG
License: Apache-2.0 license
License-File: LICENSE
Keywords: cli,command,fulfillment,interface,line,marketplace,softwareone,utility
Classifier: Development Status :: 5 - Production/Stable
Classifier: Environment :: Console
Classifier: Operating System :: POSIX :: Linux
Classifier: Programming Language :: Python :: 3.12
Classifier: Topic :: Utilities
Requires-Python: <4,>=3.12
Requires-Dist: dependency-injector==4.48.*
Requires-Dist: openpyxl==3.1.*
Requires-Dist: pydantic==2.11.*
Requires-Dist: pyfiglet==1.0.*
Requires-Dist: python-dateutil==2.9.*
Requires-Dist: requests-toolbelt==1.0.*
Requires-Dist: requests==2.32.*
Requires-Dist: typer==0.15.*
